convopyro/__init__.py
convopyro-0.5.dist-info/LICENSE
convopyro-0.5.dist-info/METADATA
convopyro-0.5.dist-info/WHEEL
convopyro-0.5.dist-info/top_level.txt
convopyro-0.5.dist-info/RECORD
