Metadata-Version: 2.1
Name: convopyro
Version: 0.5
Summary: A conversation plugin class for pyrogram using inbuild Update Handlers
Home-page: https://github.com/Ripeey/Conversation-Pyrogram
Author: Ripe
Author-email: ripeey@protonmail.com
License: MIT
Classifier: Programming Language :: Python :: 3
Classifier: License :: OSI Approved :: MIT License
Classifier: Operating System :: OS Independent
Requires-Python: >=3.6
License-File: LICENSE
